deformaug3d/__init__.py
deformaug3d-0.1.1.dist-info/METADATA
deformaug3d-0.1.1.dist-info/WHEEL
deformaug3d-0.1.1.dist-info/top_level.txt
deformaug3d-0.1.1.dist-info/RECORD
