Metadata-Version: 2.2
Name: deformaug3d
Version: 0.1.1
Summary: A package for 3D volume augmentation with configurable parameters
Home-page: https://github.com/haifangong/deformaug3d
Author: Haifan Gong
Author-email: haifangong@outlook.com
Classifier: Programming Language :: Python :: 3
Classifier: Operating System :: OS Independent
Requires-Python: >=3.6
Requires-Dist: torch
Dynamic: author
Dynamic: author-email
Dynamic: classifier
Dynamic: description
Dynamic: description-content-type
Dynamic: home-page
Dynamic: requires-dist
Dynamic: requires-python
Dynamic: summary
